clean_csvs.py
clean_csv_tool-1.0.0.dist-info/METADATA
clean_csv_tool-1.0.0.dist-info/WHEEL
clean_csv_tool-1.0.0.dist-info/entry_points.txt
clean_csv_tool-1.0.0.dist-info/top_level.txt
clean_csv_tool-1.0.0.dist-info/RECORD
