Metadata-Version: 2.4
Name: clean-csv-tool
Version: 1.0.0
Summary: A utility for cleaning and normalizing CSV files
Author: Shawna Staff
License-Expression: MIT
Project-URL: Homepage, https://github.com/ShawnaRStaff/csv-cleaner
Project-URL: Repository, https://github.com/ShawnaRStaff/csv-cleaner
Keywords: csv,data-cleaning,etl,data-processing
Classifier: Development Status :: 4 - Beta
Classifier: Intended Audience :: Developers
Classifier: Programming Language :: Python :: 3
Classifier: Programming Language :: Python :: 3.9
Classifier: Programming Language :: Python :: 3.10
Classifier: Programming Language :: Python :: 3.11
Classifier: Programming Language :: Python :: 3.12
Classifier: Topic :: Text Processing
Classifier: Topic :: Utilities
Requires-Python: >=3.9
Provides-Extra: dev
Requires-Dist: pytest>=7.0.0; extra == "dev"
